pyfwimagebuilder/__init__.py
pyfwimagebuilder/avrbuilder.py
pyfwimagebuilder/builder.py
pyfwimagebuilder/decoder.py
pyfwimagebuilder/imagebuilder.py
pyfwimagebuilder/logging.yaml
pyfwimagebuilder/mcu32builder.py
pyfwimagebuilder/mcu8builder.py
pyfwimagebuilder/pic16builder.py
pyfwimagebuilder/pic18builder.py
pyfwimagebuilder/pyfwimagebuilder.py
pyfwimagebuilder/pyfwimagebuilder_main.py
pyfwimagebuilder/status_codes.py
pyfwimagebuilder-1.3.0.16.dist-info/licenses/LICENSE.txt
pyfwimagebuilder-1.3.0.16.dist-info/METADATA
pyfwimagebuilder-1.3.0.16.dist-info/WHEEL
pyfwimagebuilder-1.3.0.16.dist-info/entry_points.txt
pyfwimagebuilder-1.3.0.16.dist-info/top_level.txt
pyfwimagebuilder-1.3.0.16.dist-info/RECORD
