Metadata-Version: 2.4
Name: pyfwimagebuilder
Version: 1.3.0.16
Summary: Firmware image builder for Microchip mdfu bootloaders
Author-email: Microchip Technology <support@microchip.com>
License: MIT
Project-URL: Homepage, https://www.microchip.com
Keywords: Microchip,bootloader,PIC,AVR,pymdfu
Classifier: Development Status :: 4 - Beta
Classifier: Intended Audience :: Developers
Classifier: Topic :: Software Development :: Embedded Systems
Classifier: Programming Language :: Python :: 3
Classifier: Programming Language :: Python :: 3.9
Classifier: Programming Language :: Python :: 3.10
Classifier: Programming Language :: Python :: 3.11
Classifier: Programming Language :: Python :: 3.12
Classifier: Programming Language :: Python :: 3.13
Classifier: Operating System :: Microsoft :: Windows
Classifier: Operating System :: POSIX :: Linux
Classifier: Operating System :: MacOS
Classifier: Operating System :: OS Independent
Classifier: License :: OSI Approved :: MIT License
Requires-Python: >=3.8
License-File: LICENSE.txt
Requires-Dist: toml
Requires-Dist: pyyaml
Requires-Dist: appdirs
Requires-Dist: hexdump2
Requires-Dist: intelhex
Requires-Dist: packaging
Provides-Extra: dev
Requires-Dist: pylint>=2.15; extra == "dev"
Provides-Extra: test
Requires-Dist: mock; extra == "test"
Requires-Dist: pytest; extra == "test"
Provides-Extra: doc
Requires-Dist: mock; extra == "doc"
Requires-Dist: sphinx; extra == "doc"
Dynamic: license-file
